russell/__init__.py
russell/config.py
russell/constants.py
russell/date_utils.py
russell/exceptions.py
russell/log.py
russell/main.py
russell/cli/__init__.py
russell/cli/auth.py
russell/cli/data.py
russell/cli/experiment.py
russell/cli/project.py
russell/cli/run.py
russell/cli/utils.py
russell/cli/version.py
russell/client/__init__.py
russell/client/auth.py
russell/client/base.py
russell/client/common.py
russell/client/data.py
russell/client/env.py
russell/client/experiment.py
russell/client/files.py
russell/client/log.py
russell/client/module.py
russell/client/project.py
russell/client/service.py
russell/client/task_instance.py
russell/client/usage.py
russell/client/version.py
russell/development/__init__.py
russell/development/dev.py
russell/development/local.py
russell/manager/__init__.py
russell/manager/auth_config.py
russell/manager/data_config.py
russell/manager/experiment_config.py
russell/manager/russell_ignore.py
russell/model/__init__.py
russell/model/access_token.py
russell/model/base.py
russell/model/credentials.py
russell/model/env.py
russell/model/experiment.py
russell/model/experiment_config.py
russell/model/module.py
russell/model/service.py
russell/model/task_instance.py
russell/model/user.py
russell/model/version.py
xxxy_test-0.7.10.dist-info/DESCRIPTION.rst
xxxy_test-0.7.10.dist-info/METADATA
xxxy_test-0.7.10.dist-info/RECORD
xxxy_test-0.7.10.dist-info/WHEEL
xxxy_test-0.7.10.dist-info/entry_points.txt
xxxy_test-0.7.10.dist-info/metadata.json
xxxy_test-0.7.10.dist-info/top_level.txt
